knwkrma_utils/__init__.py
knwkrma_utils/data.py
knwkrma_utils/package.py
knwkrma_utils/terminal.py
knwkrma_utils-1.0.0.dist-info/LICENSE
knwkrma_utils-1.0.0.dist-info/METADATA
knwkrma_utils-1.0.0.dist-info/WHEEL
knwkrma_utils-1.0.0.dist-info/RECORD
